hangar_sdk/__init__.py
hangar_sdk/core/__init__.py
hangar_sdk/core/blocks/__init__.py
hangar_sdk/core/blocks/aws_blocks.py
hangar_sdk/core/blocks/py.typed
hangar_sdk/core/py.typed
hangar_sdk/core/rbac/__init__.py
hangar_sdk/core/rbac/aws/__init__.py
hangar_sdk/core/rbac/aws/base_type.py
hangar_sdk/core/rbac/aws/iam-definition.json
hangar_sdk/core/rbac/aws/iam_types/aws_a2c.py
hangar_sdk/core/rbac/aws/iam_types/aws_a4b.py
hangar_sdk/core/rbac/aws/iam_types/aws_access_analyzer.py
hangar_sdk/core/rbac/aws/iam_types/aws_account.py
hangar_sdk/core/rbac/aws/iam_types/aws_acm.py
hangar_sdk/core/rbac/aws/iam_types/aws_acm_pca.py
hangar_sdk/core/rbac/aws/iam_types/aws_activate.py
hangar_sdk/core/rbac/aws/iam_types/aws_airflow.py
hangar_sdk/core/rbac/aws/iam_types/aws_amplify.py
hangar_sdk/core/rbac/aws/iam_types/aws_amplifybackend.py
hangar_sdk/core/rbac/aws/iam_types/aws_amplifyuibuilder.py
hangar_sdk/core/rbac/aws/iam_types/aws_aoss.py
hangar_sdk/core/rbac/aws/iam_types/aws_apigateway.py
hangar_sdk/core/rbac/aws/iam_types/aws_app_integrations.py
hangar_sdk/core/rbac/aws/iam_types/aws_appconfig.py
hangar_sdk/core/rbac/aws/iam_types/aws_appfabric.py
hangar_sdk/core/rbac/aws/iam_types/aws_appflow.py
hangar_sdk/core/rbac/aws/iam_types/aws_application_autoscaling.py
hangar_sdk/core/rbac/aws/iam_types/aws_application_cost_profiler.py
hangar_sdk/core/rbac/aws/iam_types/aws_application_transformation.py
hangar_sdk/core/rbac/aws/iam_types/aws_applicationinsights.py
hangar_sdk/core/rbac/aws/iam_types/aws_appmesh.py
hangar_sdk/core/rbac/aws/iam_types/aws_appmesh_preview.py
hangar_sdk/core/rbac/aws/iam_types/aws_apprunner.py
hangar_sdk/core/rbac/aws/iam_types/aws_appstream.py
hangar_sdk/core/rbac/aws/iam_types/aws_appsync.py
hangar_sdk/core/rbac/aws/iam_types/aws_aps.py
hangar_sdk/core/rbac/aws/iam_types/aws_arc_zonal_shift.py
hangar_sdk/core/rbac/aws/iam_types/aws_arsenal.py
hangar_sdk/core/rbac/aws/iam_types/aws_artifact.py
hangar_sdk/core/rbac/aws/iam_types/aws_athena.py
hangar_sdk-0.0.28.dist-info/LICENSE
hangar_sdk-0.0.28.dist-info/METADATA
hangar_sdk-0.0.28.dist-info/WHEEL
hangar_sdk-0.0.28.dist-info/RECORD
