Metadata-Version: 2.1
Name: hangar-sdk
Version: 0.0.28
Summary: SDK for hangar cloud.
License: APACHE 2.0
Author: Mihir Chintawar
Author-email: mihir@tryhangar.com
Requires-Python: >=3.8,<4.0
Classifier: License :: Other/Proprietary License
Classifier: Programming Language :: Python :: 3
Classifier: Programming Language :: Python :: 3.8
Classifier: Programming Language :: Python :: 3.9
Classifier: Programming Language :: Python :: 3.10
Classifier: Programming Language :: Python :: 3.11
Requires-Dist: aioboto3 (>=12.3.0,<13.0.0)
Requires-Dist: attrs (>=23.2.0,<24.0.0)
Requires-Dist: boto3 (==1.34.34)
Requires-Dist: boto3-stubs (>=1.34.55,<2.0.0)
Requires-Dist: botocore-stubs (>=1.34.56,<2.0.0)
Requires-Dist: cryptography (>=42.0.3,<43.0.0)
Requires-Dist: mypy (>=1.8.0,<2.0.0)
Requires-Dist: paramiko (>=3.4.0,<4.0.0)
Requires-Dist: plumbum (>=1.8.2,<2.0.0)
Requires-Dist: pytest (>=8.0.2,<9.0.0)
Requires-Dist: requests (>=2.31.0,<3.0.0)
